bilibili_subtitle_fetch/download_audio.py
bilibili_subtitle_fetch/generate_subtitles.py
bilibili_subtitle_fetch/server.py
bilibili_subtitle_fetch-0.2.7.dist-info/METADATA
bilibili_subtitle_fetch-0.2.7.dist-info/WHEEL
bilibili_subtitle_fetch-0.2.7.dist-info/entry_points.txt
bilibili_subtitle_fetch-0.2.7.dist-info/licenses/LICENSE
bilibili_subtitle_fetch-0.2.7.dist-info/RECORD
