Metadata-Version: 2.4
Name: bilibili-subtitle-fetch
Version: 0.2.7
Summary: An MCP (Model Context Protocol) server that allows you to fetch subtitles for Bilibili videos.
Author: Initsnow
License: GPLv3
License-File: LICENSE
Keywords: automation,http,llm,mcp
Requires-Python: <3.14,>=3.10
Requires-Dist: bilibili-api-python>=17.1.4
Requires-Dist: faster-whisper>=1.2.1
Requires-Dist: httpx>=0.27.0
Requires-Dist: mcp[cli]>=1.6.0
